README.txt
setup.py
Products/__init__.py
Products.LTOnlineTest.egg-info/PKG-INFO
Products.LTOnlineTest.egg-info/SOURCES.txt
Products.LTOnlineTest.egg-info/dependency_links.txt
Products.LTOnlineTest.egg-info/namespace_packages.txt
Products.LTOnlineTest.egg-info/not-zip-safe
Products.LTOnlineTest.egg-info/requires.txt
Products.LTOnlineTest.egg-info/top_level.txt
Products/LTOnlineTest/Article.py
Products/LTOnlineTest/OnlineTest.py
Products/LTOnlineTest/OnlineTestTool.py
Products/LTOnlineTest/Question.py
Products/LTOnlineTest/__init__.py
Products/LTOnlineTest/config.py
Products/LTOnlineTest/version.txt
Products/LTOnlineTest/Extensions/Install.py
Products/LTOnlineTest/skins/ltonlinetest/onlinetest_attempt.pt
Products/LTOnlineTest/skins/ltonlinetest/onlinetest_correct.gif
Products/LTOnlineTest/skins/ltonlinetest/onlinetest_correct.gif.properties
Products/LTOnlineTest/skins/ltonlinetest/onlinetest_getquestionlist.py
Products/LTOnlineTest/skins/ltonlinetest/onlinetest_icon.gif
Products/LTOnlineTest/skins/ltonlinetest/onlinetest_icon.gif.properties
Products/LTOnlineTest/skins/ltonlinetest/onlinetest_logo.gif
Products/LTOnlineTest/skins/ltonlinetest/onlinetest_logo.gif.properties
Products/LTOnlineTest/skins/ltonlinetest/onlinetest_process.py
Products/LTOnlineTest/skins/ltonlinetest/onlinetest_report.pt
Products/LTOnlineTest/skins/ltonlinetest/onlinetest_report.pt.metadata
Products/LTOnlineTest/skins/ltonlinetest/onlinetest_results.pt
Products/LTOnlineTest/skins/ltonlinetest/onlinetest_view.properties
Products/LTOnlineTest/skins/ltonlinetest/onlinetest_view.pt
Products/LTOnlineTest/skins/ltonlinetest/onlinetest_wrong.gif
Products/LTOnlineTest/skins/ltonlinetest/onlinetest_wrong.gif.properties
Products/LTOnlineTest/skins/ltonlinetest/question_icon.gif
Products/LTOnlineTest/skins/ltonlinetest/question_icon.jpg
Products/LTOnlineTest/skins/ltonlinetest/question_view.pt
