Metadata-Version: 1.0
Name: Products.LTOnlineTest
Version: 0.2.4
Summary: An online Quiz product for CMF & Plone.
Home-page: http://lawtec.net/projects/ltonlinetest
Author: Anton Hughes
Author-email: antonh@lawtec.net
License: GPL
Keywords: Zope CMF Plone online quiz
Platform: UNKNOWN
Classifier: Framework :: Plone
Classifier: Framework :: Zope2
Classifier: Programming Language :: Python
